{
  "type": "PowerTurret",
  "name": "arcus-turret-advanced",
  "localizedName": "Arcus Advanced",
  "size": 1,
  "health": 800,
  "reload": 20,
  "range": 160,
  "shootCone": 30,
  "hasPower": true,
  "consumes": {
    "power": 0.9
  },
  "shootType": {
    "type": "LightningBulletType",
    "damage": 25,
    "lightningLength": 160,
    "lightningAngle": 60,
    "bounce": 3,
    "bounceRange": 80,
    "frontColor": "00FFFF",
    "backColor": "66FFFF",
    "trailColor": "00FFFF",
    "status": "shocked"
  },
  "requirements": [
    { "item": "copper", "amount": 150 },
    { "item": "lead", "amount": 100 },
    { "item": "graphite", "amount": 80 }
  ],
  "category": "turret",
  "research": {
    "parent": "arcus-lightning-v1",
    "requirements": [
      { "item": "copper", "amount": 450 },
      { "item": "lead", "amount": 300 },
      { "item": "graphite", "amount": 240 }
    ]
  }
}