{
  "type": "ItemTurret",
  "name": "disruptor-lance",
  "localizedName": "Disruptor Lance",
  "description": "Extrem weitreichendes Störgeschütz. Verursacht kaum Schaden, schleudert Gegner jedoch massiv zurück.",

  "size": 3,
  "health": 1600,

  "range": 520,
  "reload": 180,
  "rotateSpeed": 1.2,
  "shootCone": 2,

  "recoil": 3,
  "shootShake": 4,

  "ammoPerShot": 1,
  "shootSound": "shootBig",

  "ammoTypes": {
    "copper": {
      "type": "MissileBulletType",

      "damage": 20,

      "speed": 4,
      "lifetime": 140,

      "homingPower": 0.08,
      "homingRange": 160,

      "knockback": 6.5,

      "width": 7,
      "height": 9,

      "trailLength": 12,
      "trailWidth": 2,

      "hitEffect": "blastExplosion",
      "despawnEffect": "smokeCloud",

      "collidesAir": true,
      "collidesGround": true,

      "frontColor": "A5D6FFFF",
      "backColor": "1E88E5FF"
    }
  },

  "requirements": [
    { "item": "copper", "amount": 300 },
    { "item": "lead", "amount": 250 },
    { "item": "silicon", "amount": 180 }
  ],

  "category": "turret",

  "research": {
    "parent": "salvo",
    "requirements": [
      { "item": "copper", "amount": 1200 },
      { "item": "lead", "amount": 900 },
      { "item": "silicon", "amount": 600 }
    ]
  }
}